resourceful/__init__.py
resourceful/resourceful.py
resourceful-0.1.4.dist-info/LICENSE
resourceful-0.1.4.dist-info/WHEEL
resourceful-0.1.4.dist-info/METADATA
resourceful-0.1.4.dist-info/RECORD
