Metadata-Version: 2.1
Name: resourceful
Version: 0.1.4
Summary: Human friendly HTTP client for RESTful APIs
Home-page: https://github.com/logileifs/resourceful
License: MIT
Keywords: http,restful
Author: Logi Leifsson
Author-email: logileifs@gmail.com
Requires-Python: >=3.8,<4.0
Classifier: License :: OSI Approved :: MIT License
Classifier: Programming Language :: Python :: 3
Classifier: Programming Language :: Python :: 3.8
Classifier: Programming Language :: Python :: 3.9
Classifier: Programming Language :: Python :: 3.10
Requires-Dist: httpx (>=0.23.0,<0.24.0)
Project-URL: Repository, https://github.com/logileifs/resourceful
